Metadata-Version: 2.2
Name: python_fib_study
Version: 0.0.2
Summary: Calculates a Fibonacci number
Home-page: https://github.com/Neznakomec16/python-fib
Author: neznakomec16
Requires-Python: >=3
License-File: LICENSE
Requires-Dist: PyYAML>=4.1.2
Requires-Dist: dill>=0.2.8
Provides-Extra: server
Requires-Dist: Flask>=1.0.0; extra == "server"
Dynamic: author
Dynamic: description
Dynamic: home-page
Dynamic: provides-extra
Dynamic: requires-dist
Dynamic: requires-python
Dynamic: summary
